lingkar33423312/__init__.py
lingkar33423312/circle_calculator.py
lingkar33423312-0.0.1.dist-info/METADATA
lingkar33423312-0.0.1.dist-info/WHEEL
lingkar33423312-0.0.1.dist-info/top_level.txt
lingkar33423312-0.0.1.dist-info/RECORD
